{
  "name": "Log",
  "base": "PersistedModel",
  "idInjection": true,
  "options": {
    "validateUpsert": true
  },
  "properties": {
    "date": {
      "type": "date",
      "required": true
    },
    "diff": {
      "type": "number",
      "required": true
    },
    "isNormal":{
      "type": "boolean",
      "required": false
    },
    "isInAdvance":{
      "type": "boolean",
      "required": false
    },
    "isLate": {
      "type": "boolean",
      "required": false
    }
  },
  "validations": [],
  "relations": {},
  "acls": [],
  "methods": {}
}
